tensorshow/__init__.py
tensorshow/tensorshow.py
tensorshow-0.0.2.dist-info/LICENSE
tensorshow-0.0.2.dist-info/METADATA
tensorshow-0.0.2.dist-info/WHEEL
tensorshow-0.0.2.dist-info/top_level.txt
tensorshow-0.0.2.dist-info/RECORD
