Metadata-Version: 2.1
Name: tensorshow
Version: 0.0.2
Summary: A python module and commaned line tool for inspecting TFRecords.
Home-page: https://github.com/joelypoley/tensorshow
Author: Joel Laity
Author-email: joel.laity@gmail.com
License: UNKNOWN
Platform: UNKNOWN
Classifier: Programming Language :: Python :: 3.6
Classifier: License :: OSI Approved :: MIT License
Classifier: Operating System :: OS Independent
Requires-Dist: fleep
Requires-Dist: ipython
Requires-Dist: pandas
Requires-Dist: pillow
Requires-Dist: tensorflow
